January/January.py
January/__init__.py
January-0.5.dist-info/LICENSE
January-0.5.dist-info/METADATA
January-0.5.dist-info/WHEEL
January-0.5.dist-info/top_level.txt
January-0.5.dist-info/RECORD
